Workbook

Sheet Parts Inventory
A1: PRINTEX ENGINEERS
A2: Parts Inventory & Price List
A3: Transcribed from the handwritten parts register (Columns A-F). Buying prices in USD; selling prices in KES.
A5: Item No. | B5: Register Column | C5: Category | D5: Part Description | E5: Part No. | F5: Qty | G5: Unit | H5: Buying Price (USD) | I5: Selling Price (KES) | J5: Stock Value (USD) | K5: Potential Sales (KES) | L5: Notes
A6: 1 | B6: A | C6: Valves, Cylinders & Pistons | D6: Control Valve | E6: M2.184.1111/05 | F6: 9 | G6: Pcs | H6: 30 | I6: 12400 | J6: =IF(AND(ISNUMBER(F6),ISNUMBER(H6)),F6*H6,"") -> 270 | K6: =IF(AND(ISNUMBER(F6),ISNUMBER(I6)),F6*I6,"") -> 111600
A7: 2 | B7: A | C7: Valves, Cylinders & Pistons | D7: Control Valve | E7: M2.184.1121/05 | F7: 9 | G7: Pcs | H7: 30 | I7: 12400 | J7: =IF(AND(ISNUMBER(F7),ISNUMBER(H7)),F7*H7,"") -> 270 | K7: =IF(AND(ISNUMBER(F7),ISNUMBER(I7)),F7*I7,"") -> 111600
A8: 3 | B8: A | C8: Valves, Cylinders & Pistons | D8: Control Valve | E8: M2.184.1131 | F8: 3 | G8: Pcs | I8: 16250 | J8: =IF(AND(ISNUMBER(F8),ISNUMBER(H8)),F8*H8,"") | K8: =IF(AND(ISNUMBER(F8),ISNUMBER(I8)),F8*I8,"") -> 48750 | L8: Buying price not recorded
A9: 4 | B9: A | C9: Valves, Cylinders & Pistons | D9: Vibrator Valve | E9: G2.184.0060 | F9: 10 | G9: Pcs | H9: 35 | I9: 14800 | J9: =IF(AND(ISNUMBER(F9),ISNUMBER(H9)),F9*H9,"") -> 350 | K9: =IF(AND(ISNUMBER(F9),ISNUMBER(I9)),F9*I9,"") -> 148000
A10: 5 | B10: A | C10: Valves, Cylinders & Pistons | D10: Vibrator Valve | E10: G2.184.0040 | F10: 6 | G10: Pcs | H10: 34 | I10: 15200 | J10: =IF(AND(ISNUMBER(F10),ISNUMBER(H10)),F10*H10,"") -> 204 | K10: =IF(AND(ISNUMBER(F10),ISNUMBER(I10)),F10*I10,"") -> 91200
A11: 6 | B11: A | C11: Valves, Cylinders & Pistons | D11: Vibrator Valve | E11: 61.184.1133 | F11: 6 | G11: Pcs | H11: 35 | I11: 14800 | J11: =IF(AND(ISNUMBER(F11),ISNUMBER(H11)),F11*H11,"") -> 210 | K11: =IF(AND(ISNUMBER(F11),ISNUMBER(I11)),F11*I11,"") -> 88800
A12: 7 | B12: A | C12: Valves, Cylinders & Pistons | D12: Vibrator Valve | E12: 61.184.1131 | F12: 3 | G12: Pcs | H12: 35 | I12: 14800 | J12: =IF(AND(ISNUMBER(F12),ISNUMBER(H12)),F12*H12,"") -> 105 | K12: =IF(AND(ISNUMBER(F12),ISNUMBER(I12)),F12*I12,"") -> 44400
A13: 8 | B13: A | C13: Valves, Cylinders & Pistons | D13: Vibrator Valve | E13: L2.335.051 | F13: 2 | G13: Pcs | H13: 35 | I13: 14800 | J13: =IF(AND(ISNUMBER(F13),ISNUMBER(H13)),F13*H13,"") -> 70 | K13: =IF(AND(ISNUMBER(F13),ISNUMBER(I13)),F13*I13,"") -> 29600
A14: 9 | B14: A | C14: Valves, Cylinders & Pistons | D14: Vibrator Valve | E14: M2.184.1071 | F14: 3 | G14: Pcs | H14: 35 | I14: 15200 | J14: =IF(AND(ISNUMBER(F14),ISNUMBER(H14)),F14*H14,"") -> 105 | K14: =IF(AND(ISNUMBER(F14),ISNUMBER(I14)),F14*I14,"") -> 45600
A15: 10 | B15: A | C15: Valves, Cylinders & Pistons | D15: Vibrator Valve | E15: 61.184.1171 | F15: 3 | G15: Pcs | H15: 35 | I15: 14800 | J15: =IF(AND(ISNUMBER(F15),ISNUMBER(H15)),F15*H15,"") -> 105 | K15: =IF(AND(ISNUMBER(F15),ISNUMBER(I15)),F15*I15,"") -> 44400
A16: 11 | B16: A | C16: Valves, Cylinders & Pistons | D16: Solenoid Valve | E16: 61.184.1311 | F16: 13 | G16: Pcs | H16: 28 | I16: 18130 | J16: =IF(AND(ISNUMBER(F16),ISNUMBER(H16)),F16*H16,"") -> 364 | K16: =IF(AND(ISNUMBER(F16),ISNUMBER(I16)),F16*I16,"") -> 235690
A17: 12 | B17: A | C17: Valves, Cylinders & Pistons | D17: Solenoid Valve | E17: 98.184.1051 | F17: 14 | G17: Pcs | H17: 28 | I17: 18620 | J17: =IF(AND(ISNUMBER(F17),ISNUMBER(H17)),F17*H17,"") -> 392 | K17: =IF(AND(ISNUMBER(F17),ISNUMBER(I17)),F17*I17,"") -> 260680 | L17: Part no. written over a crossed-out entry
A18: 13 | B18: A | C18: Valves, Cylinders & Pistons | D18: Pneumatic Valve | E18: L2.334.002 | F18: 2 | G18: Pcs | J18: =IF(AND(ISNUMBER(F18),ISNUMBER(H18)),F18*H18,"") | K18: =IF(AND(ISNUMBER(F18),ISNUMBER(I18)),F18*I18,"") | L18: No prices recorded
A19: 14 | B19: A | C19: Valves, Cylinders & Pistons | D19: Pneumatic Valve | E19: 87.334.010 | F19: 3 | G19: Pcs | H19: 18 | I19: 18500 | J19: =IF(AND(ISNUMBER(F19),ISNUMBER(H19)),F19*H19,"") -> 54 | K19: =IF(AND(ISNUMBER(F19),ISNUMBER(I19)),F19*I19,"") -> 55500
A20: 15 | B20: A | C20: Valves, Cylinders & Pistons | D20: Pneumatic Valve | E20: 00.580.3909 | F20: 11 | G20: Pcs | H20: 25 | I20: 18250 | J20: =IF(AND(ISNUMBER(F20),ISNUMBER(H20)),F20*H20,"") -> 275 | K20: =IF(AND(ISNUMBER(F20),ISNUMBER(I20)),F20*I20,"") -> 200750
A21: 16 | B21: A | C21: Valves, Cylinders & Pistons | D21: Pneumatic Valve | E21: 00.580.3930 | F21: 2 | G21: Pcs | H21: 18 | J21: =IF(AND(ISNUMBER(F21),ISNUMBER(H21)),F21*H21,"") -> 36 | K21: =IF(AND(ISNUMBER(F21),ISNUMBER(I21)),F21*I21,"") | L21: Selling price not recorded
A22: 17 | B22: A | C22: Valves, Cylinders & Pistons | D22: Pneumatic Cylinder | E22: F4.334.044 | F22: 1 | G22: Pc | H22: 25 | I22: 18250 | J22: =IF(AND(ISNUMBER(F22),ISNUMBER(H22)),F22*H22,"") -> 25 | K22: =IF(AND(ISNUMBER(F22),ISNUMBER(I22)),F22*I22,"") -> 18250
A23: 18 | B23: A | C23: Valves, Cylinders & Pistons | D23: Control Valve | E23: 61.184.1191 | F23: 1 | G23: Pc | J23: =IF(AND(ISNUMBER(F23),ISNUMBER(H23)),F23*H23,"") | K23: =IF(AND(ISNUMBER(F23),ISNUMBER(I23)),F23*I23,"") | L23: No prices recorded
A24: 19 | B24: A | C24: Valves, Cylinders & Pistons | D24: Cylinder Valve | E24: F4.334.036/03 | F24: 1 | G24: Pc | H24: 26 | I24: 14500 | J24: =IF(AND(ISNUMBER(F24),ISNUMBER(H24)),F24*H24,"") -> 26 | K24: =IF(AND(ISNUMBER(F24),ISNUMBER(I24)),F24*I24,"") -> 14500
A25: 20 | B25: A | C25: Valves, Cylinders & Pistons | D25: Solenoid Valve | E25: G4.334.004/03 | F25: 1 | G25: Pc | H25: 26 | I25: 14500 | J25: =IF(AND(ISNUMBER(F25),ISNUMBER(H25)),F25*H25,"") -> 26 | K25: =IF(AND(ISNUMBER(F25),ISNUMBER(I25)),F25*I25,"") -> 14500
A26: 21 | B26: A | C26: Valves, Cylinders & Pistons | D26: Piston | E26: L2.007.531 | F26: 1 | G26: Pc | H26: 210 | I26: 65000 | J26: =IF(AND(ISNUMBER(F26),ISNUMBER(H26)),F26*H26,"") -> 210 | K26: =IF(AND(ISNUMBER(F26),ISNUMBER(I26)),F26*I26,"") -> 65000
A27: 22 | B27: A | C27: Valves, Cylinders & Pistons | D27: Solenoid Valve | E27: 87.334.001/02 | F27: 1 | G27: Pc | J27: =IF(AND(ISNUMBER(F27),ISNUMBER(H27)),F27*H27,"") | K27: =IF(AND(ISNUMBER(F27),ISNUMBER(I27)),F27*I27,"") | L27: No prices recorded
A28: 23 | B28: A | C28: Valves, Cylinders & Pistons | D28: Pneumatic Cylinder | E28: 00.580.4275 | F28: 1 | G28: Pc | H28: 27 | J28: =IF(AND(ISNUMBER(F28),ISNUMBER(H28)),F28*H28,"") -> 27 | K28: =IF(AND(ISNUMBER(F28),ISNUMBER(I28)),F28*I28,"") | L28: Selling price not recorded
A29: 24 | B29: A | C29: Valves, Cylinders & Pistons | D29: Solenoid Valve | E29: F7.335.002 | F29: 1 | G29: Pc | H29: 26 | I29: 14500 | J29: =IF(AND(ISNUMBER(F29),ISNUMBER(H29)),F29*H29,"") -> 26 | K29: =IF(AND(ISNUMBER(F29),ISNUMBER(I29)),F29*I29,"") -> 14500
A30: 25 | B30: A | C30: Valves, Cylinders & Pistons | D30: Solenoid Valve | E30: 00.580.4300/02 | F30: 2 | G30: Pcs | H30: 14 | I30: 14500 | J30: =IF(AND(ISNUMBER(F30),ISNUMBER(H30)),F30*H30,"") -> 28 | K30: =IF(AND(ISNUMBER(F30),ISNUMBER(I30)),F30*I30,"") -> 29000
A31: 26 | B31: A | C31: Valves, Cylinders & Pistons | D31: Pneumatic Valve | E31: 87.334.001 | F31: 4 | G31: Pcs | H31: 25 | I31: 18250 | J31: =IF(AND(ISNUMBER(F31),ISNUMBER(H31)),F31*H31,"") -> 100 | K31: =IF(AND(ISNUMBER(F31),ISNUMBER(I31)),F31*I31,"") -> 73000
A32: 27 | B32: A | C32: Valves, Cylinders & Pistons | D32: Piston | F32: 1 | G32: Pc | H32: 60 | I32: 26800 | J32: =IF(AND(ISNUMBER(F32),ISNUMBER(H32)),F32*H32,"") -> 60 | K32: =IF(AND(ISNUMBER(F32),ISNUMBER(I32)),F32*I32,"") -> 26800 | L32: Part no. not recorded
A33: 28 | B33: B | C33: Bellows, Diaphragms & Spindles | D33: SM52 Bellows | F33: 16 | G33: Pcs | H33: 4.2 | I33: 3000 | J33: =IF(AND(ISNUMBER(F33),ISNUMBER(H33)),F33*H33,"") -> 67.2 | K33: =IF(AND(ISNUMBER(F33),ISNUMBER(I33)),F33*I33,"") -> 48000
A34: 29 | B34: B | C34: Bellows, Diaphragms & Spindles | D34: SM74 Bellows | F34: 20 | G34: Pcs | H34: 4.6 | I34: 4250 | J34: =IF(AND(ISNUMBER(F34),ISNUMBER(H34)),F34*H34,"") -> 92 | K34: =IF(AND(ISNUMBER(F34),ISNUMBER(I34)),F34*I34,"") -> 85000
A35: 30 | B35: B | C35: Bellows, Diaphragms & Spindles | D35: CD74 Bellows | F35: 19 | G35: Pcs | H35: 4.6 | I35: 4950 | J35: =IF(AND(ISNUMBER(F35),ISNUMBER(H35)),F35*H35,"") -> 87.4 | K35: =IF(AND(ISNUMBER(F35),ISNUMBER(I35)),F35*I35,"") -> 94050
A36: 31 | B36: B | C36: Bellows, Diaphragms & Spindles | D36: CD/XL105 Bellows | F36: 4 | G36: Pcs | H36: 4.8 | I36: 6050 | J36: =IF(AND(ISNUMBER(F36),ISNUMBER(H36)),F36*H36,"") -> 19.2 | K36: =IF(AND(ISNUMBER(F36),ISNUMBER(I36)),F36*I36,"") -> 24200
A37: 32 | B37: B | C37: Bellows, Diaphragms & Spindles | D37: PM74 Bellows | F37: 1 | G37: Pc | H37: 2.8 | I37: 3795 | J37: =IF(AND(ISNUMBER(F37),ISNUMBER(H37)),F37*H37,"") -> 2.8 | K37: =IF(AND(ISNUMBER(F37),ISNUMBER(I37)),F37*I37,"") -> 3795
A38: 33 | B38: B | C38: Bellows, Diaphragms & Spindles | D38: SM52 Autoplate Diaphragm | F38: 17 | G38: Pcs | H38: 14 | I38: 9450 | J38: =IF(AND(ISNUMBER(F38),ISNUMBER(H38)),F38*H38,"") -> 238 | K38: =IF(AND(ISNUMBER(F38),ISNUMBER(I38)),F38*I38,"") -> 160650
A39: 34 | B39: B | C39: Bellows, Diaphragms & Spindles | D39: SM/CD102 Autoplate Diaphragm | F39: 9 | G39: Pcs | H39: 14 | I39: 9450 | J39: =IF(AND(ISNUMBER(F39),ISNUMBER(H39)),F39*H39,"") -> 126 | K39: =IF(AND(ISNUMBER(F39),ISNUMBER(I39)),F39*I39,"") -> 85050
A40: 35 | B40: B | C40: Bellows, Diaphragms & Spindles | D40: Technotrans | E40: DS.196.2015 | F40: 9 | G40: Pcs | H40: 11 | I40: 12750 | J40: =IF(AND(ISNUMBER(F40),ISNUMBER(H40)),F40*H40,"") -> 99 | K40: =IF(AND(ISNUMBER(F40),ISNUMBER(I40)),F40*I40,"") -> 114750
A41: 36 | B41: B | C41: Bellows, Diaphragms & Spindles | D41: Friction Wheels | E41: F4.614.5565 | F41: 18 | G41: Pcs | H41: 22 | I41: 6150 | J41: =IF(AND(ISNUMBER(F41),ISNUMBER(H41)),F41*H41,"") -> 396 | K41: =IF(AND(ISNUMBER(F41),ISNUMBER(I41)),F41*I41,"") -> 110700
A42: 37 | B42: B | C42: Bellows, Diaphragms & Spindles | D42: SM74 Autoplate Diaphragm | F42: 2 | G42: Pcs | H42: 14 | I42: 9450 | J42: =IF(AND(ISNUMBER(F42),ISNUMBER(H42)),F42*H42,"") -> 28 | K42: =IF(AND(ISNUMBER(F42),ISNUMBER(I42)),F42*I42,"") -> 18900
A43: 38 | B43: B | C43: Bellows, Diaphragms & Spindles | D43: Diaphragm Clips CPI | F43: 6 | G43: Pcs | H43: 20 | I43: 13500 | J43: =IF(AND(ISNUMBER(F43),ISNUMBER(H43)),F43*H43,"") -> 120 | K43: =IF(AND(ISNUMBER(F43),ISNUMBER(I43)),F43*I43,"") -> 81000 | L43: Suffix reads 'CPI' - verify
A44: 39 | B44: B | C44: Bellows, Diaphragms & Spindles | D44: Adjusting Spindle | E44: L2.030.412F | F44: 2 | G44: Pcs | H44: 11 | J44: =IF(AND(ISNUMBER(F44),ISNUMBER(H44)),F44*H44,"") -> 22 | K44: =IF(AND(ISNUMBER(F44),ISNUMBER(I44)),F44*I44,"") | L44: Selling price not recorded
A45: 40 | B45: B | C45: Bellows, Diaphragms & Spindles | D45: Friction Wheels CPH | F45: 3 | G45: Pcs | H45: 7.5 | I45: 6150 | J45: =IF(AND(ISNUMBER(F45),ISNUMBER(H45)),F45*H45,"") -> 22.5 | K45: =IF(AND(ISNUMBER(F45),ISNUMBER(I45)),F45*I45,"") -> 18450 | L45: Suffix reads 'CPh' - verify
A46: 41 | B46: B | C46: Bellows, Diaphragms & Spindles | D46: Adjusting Spindle SM52 | F46: 4 | G46: Pcs | H46: 10 | I46: 7500 | J46: =IF(AND(ISNUMBER(F46),ISNUMBER(H46)),F46*H46,"") -> 40 | K46: =IF(AND(ISNUMBER(F46),ISNUMBER(I46)),F46*I46,"") -> 30000
A47: 42 | B47: B | C47: Bellows, Diaphragms & Spindles | D47: Adjusting Spindle SM74 | F47: 6 | G47: Pcs | H47: 11 | I47: 9075 | J47: =IF(AND(ISNUMBER(F47),ISNUMBER(H47)),F47*H47,"") -> 66 | K47: =IF(AND(ISNUMBER(F47),ISNUMBER(I47)),F47*I47,"") -> 54450
A48: 43 | B48: B | C48: Bellows, Diaphragms & Spindles | D48: Diaphragm Clips | F48: 19 | G48: Pcs | H48: 6 | I48: 5750 | J48: =IF(AND(ISNUMBER(F48),ISNUMBER(H48)),F48*H48,"") -> 114 | K48: =IF(AND(ISNUMBER(F48),ISNUMBER(I48)),F48*I48,"") -> 109250
A49: 44 | B49: B | C49: Bellows, Diaphragms & Spindles | D49: Plate Clamp Airbag Tube | G49: Roll | H49: 6 | I49: 4950 | J49: =IF(AND(ISNUMBER(F49),ISNUMBER(H49)),F49*H49,"") | K49: =IF(AND(ISNUMBER(F49),ISNUMBER(I49)),F49*I49,"") | L49: Buying price is USD 6 per metre; stock held as a roll
A50: 45 | B50: C | C50: Suckers, Cups & Gears | D50: Rubber Sucker 38 x 13 x 0.8 mm | F50: 76 | G50: Pcs | H50: 0.2 | I50: 100 | J50: =IF(AND(ISNUMBER(F50),ISNUMBER(H50)),F50*H50,"") -> 15.2 | K50: =IF(AND(ISNUMBER(F50),ISNUMBER(I50)),F50*I50,"") -> 7600
A51: 46 | B51: C | C51: Suckers, Cups & Gears | D51: Rubber Sucker 35 x 13 x 0.8 mm | F51: 530 | G51: Pcs | H51: 0.2 | I51: 100 | J51: =IF(AND(ISNUMBER(F51),ISNUMBER(H51)),F51*H51,"") -> 106 | K51: =IF(AND(ISNUMBER(F51),ISNUMBER(I51)),F51*I51,"") -> 53000
A52: 47 | B52: C | C52: Suckers, Cups & Gears | D52: Rubber Sucker 38 x 13 x 1.3 mm | F52: 200 | G52: Pcs | H52: 0.3 | I52: 100 | J52: =IF(AND(ISNUMBER(F52),ISNUMBER(H52)),F52*H52,"") -> 60 | K52: =IF(AND(ISNUMBER(F52),ISNUMBER(I52)),F52*I52,"") -> 20000
A53: 48 | B53: C | C53: Suckers, Cups & Gears | D53: Rubber Sucker 32 x 13 x 0.8 mm | F53: 62 | G53: Pcs | H53: 0.2 | I53: 100 | J53: =IF(AND(ISNUMBER(F53),ISNUMBER(H53)),F53*H53,"") -> 12.4 | K53: =IF(AND(ISNUMBER(F53),ISNUMBER(I53)),F53*I53,"") -> 6200
A54: 49 | B54: C | C54: Suckers, Cups & Gears | D54: Rubber Sucker 30 x 13 x 0.8 mm | F54: 150 | G54: Pcs | H54: 0.2 | I54: 100 | J54: =IF(AND(ISNUMBER(F54),ISNUMBER(H54)),F54*H54,"") -> 30 | K54: =IF(AND(ISNUMBER(F54),ISNUMBER(I54)),F54*I54,"") -> 15000
A55: 50 | B55: C | C55: Suckers, Cups & Gears | D55: Rubber Sucker 35 x 13 x 1 mm | F55: 350 | G55: Pcs | H55: 0.3 | I55: 100 | J55: =IF(AND(ISNUMBER(F55),ISNUMBER(H55)),F55*H55,"") -> 105 | K55: =IF(AND(ISNUMBER(F55),ISNUMBER(I55)),F55*I55,"") -> 35000
A56: 51 | B56: C | C56: Suckers, Cups & Gears | D56: Rubber Sucker 30 x 13 x 1 mm | F56: 200 | G56: Pcs | H56: 0.2 | I56: 80 | J56: =IF(AND(ISNUMBER(F56),ISNUMBER(H56)),F56*H56,"") -> 40 | K56: =IF(AND(ISNUMBER(F56),ISNUMBER(I56)),F56*I56,"") -> 16000
A57: 52 | B57: C | C57: Suckers, Cups & Gears | D57: Rubber Sucker 43 x 13 x 1.0 mm | F57: 98 | G57: Pcs | H57: 0.3 | I57: 100 | J57: =IF(AND(ISNUMBER(F57),ISNUMBER(H57)),F57*H57,"") -> 29.4 | K57: =IF(AND(ISNUMBER(F57),ISNUMBER(I57)),F57*I57,"") -> 9800
A58: 53 | B58: C | C58: Suckers, Cups & Gears | D58: Rubber Sucker 32 x 13 x 1.2 mm | F58: 119 | G58: Pcs | H58: 3.5 | I58: 80 | J58: =IF(AND(ISNUMBER(F58),ISNUMBER(H58)),F58*H58,"") -> 416.5 | K58: =IF(AND(ISNUMBER(F58),ISNUMBER(I58)),F58*I58,"") -> 9520 | L58: Buying price revised from USD 0.2 to USD 3.5
A59: 54 | B59: C | C59: Suckers, Cups & Gears | D59: MBO Rubber Sucker 23 x 3 x 1 mm | F59: 100 | G59: Pcs | H59: 0.1 | I59: 30 | J59: =IF(AND(ISNUMBER(F59),ISNUMBER(H59)),F59*H59,"") -> 10 | K59: =IF(AND(ISNUMBER(F59),ISNUMBER(I59)),F59*I59,"") -> 3000
A60: 55 | B60: C | C60: Suckers, Cups & Gears | D60: MBO Rubber Sucker 83 x 3 x 0.8 mm | F60: 50 | G60: Pcs | H60: 0.1 | I60: 30 | J60: =IF(AND(ISNUMBER(F60),ISNUMBER(H60)),F60*H60,"") -> 5 | K60: =IF(AND(ISNUMBER(F60),ISNUMBER(I60)),F60*I60,"") -> 1500
A61: 56 | B61: C | C61: Suckers, Cups & Gears | D61: Cap Sucker Muller Martini 21 x 6 x 13 mm | F61: 500 | G61: Pcs | H61: 0.1 | I61: 350 | J61: =IF(AND(ISNUMBER(F61),ISNUMBER(H61)),F61*H61,"") -> 50 | K61: =IF(AND(ISNUMBER(F61),ISNUMBER(I61)),F61*I61,"") -> 175000
A62: 57 | B62: C | C62: Suckers, Cups & Gears | D62: Cap Sucker Muller Martini 21 x 6 x 4 mm | F62: 100 | G62: Pcs | H62: 0.1 | I62: 350 | J62: =IF(AND(ISNUMBER(F62),ISNUMBER(H62)),F62*H62,"") -> 10 | K62: =IF(AND(ISNUMBER(F62),ISNUMBER(I62)),F62*I62,"") -> 35000
A63: 58 | B63: C | C63: Suckers, Cups & Gears | D63: Block Cups 12 x 6 x 8 mm | F63: 200 | G63: Pcs | H63: 0.1 | I63: 120 | J63: =IF(AND(ISNUMBER(F63),ISNUMBER(H63)),F63*H63,"") -> 20 | K63: =IF(AND(ISNUMBER(F63),ISNUMBER(I63)),F63*I63,"") -> 24000
A64: 59 | B64: C | C64: Suckers, Cups & Gears | D64: Feeder Sucker | E64: 42.016.072(B) | F64: 196 | G64: Pcs | H64: 0.1 | I64: 100 | J64: =IF(AND(ISNUMBER(F64),ISNUMBER(H64)),F64*H64,"") -> 19.6 | K64: =IF(AND(ISNUMBER(F64),ISNUMBER(I64)),F64*I64,"") -> 19600
A65: 60 | B65: C | C65: Suckers, Cups & Gears | D65: Cup Suckers Black | F65: 100 | G65: Pcs | H65: 0.1 | I65: 350 | J65: =IF(AND(ISNUMBER(F65),ISNUMBER(H65)),F65*H65,"") -> 10 | K65: =IF(AND(ISNUMBER(F65),ISNUMBER(I65)),F65*I65,"") -> 35000
A66: 61 | B66: C | C66: Suckers, Cups & Gears | D66: Worm Gear | E66: 42.006.029 | F66: 9 | G66: Pcs | H66: 8.5 | I66: 5800 | J66: =IF(AND(ISNUMBER(F66),ISNUMBER(H66)),F66*H66,"") -> 76.5 | K66: =IF(AND(ISNUMBER(F66),ISNUMBER(I66)),F66*I66,"") -> 52200
A67: 62 | B67: C | C67: Suckers, Cups & Gears | D67: Bearing for CD74 | F67: 4 | G67: Pcs | H67: 38 | I67: 9310 | J67: =IF(AND(ISNUMBER(F67),ISNUMBER(H67)),F67*H67,"") -> 152 | K67: =IF(AND(ISNUMBER(F67),ISNUMBER(I67)),F67*I67,"") -> 37240
A68: 63 | B68: C | C68: Suckers, Cups & Gears | D68: Gears for CD74 | F68: 3 | G68: Sets | H68: 87 | I68: 30450 | J68: =IF(AND(ISNUMBER(F68),ISNUMBER(H68)),F68*H68,"") -> 261 | K68: =IF(AND(ISNUMBER(F68),ISNUMBER(I68)),F68*I68,"") -> 91350
A69: 64 | B69: C | C69: Suckers, Cups & Gears | D69: Rubber Sucker | E69: 66.028.405 | F69: 99 | G69: Pcs | J69: =IF(AND(ISNUMBER(F69),ISNUMBER(H69)),F69*H69,"") | K69: =IF(AND(ISNUMBER(F69),ISNUMBER(I69)),F69*I69,"") | L69: No prices recorded
A70: 65 | B70: C | C70: Suckers, Cups & Gears | D70: Feeder Sucker Rod | F70: 170 | G70: Pcs | H70: 10 | I70: 100 | J70: =IF(AND(ISNUMBER(F70),ISNUMBER(H70)),F70*H70,"") -> 1700 | K70: =IF(AND(ISNUMBER(F70),ISNUMBER(I70)),F70*I70,"") -> 17000 | L70: Selling price below buying price - verify
A71: 66 | B71: C | C71: Suckers, Cups & Gears | D71: Gear Worm | E71: M2.006.001 | F71: 18 | G71: Pcs | H71: 8.5 | I71: 5500 | J71: =IF(AND(ISNUMBER(F71),ISNUMBER(H71)),F71*H71,"") -> 153 | K71: =IF(AND(ISNUMBER(F71),ISNUMBER(I71)),F71*I71,"") -> 99000
A72: 67 | B72: C | C72: Suckers, Cups & Gears | D72: Rubber Sucker 45 x 13 x 0.8 mm | F72: 500 | G72: Pcs | H72: 10 | J72: =IF(AND(ISNUMBER(F72),ISNUMBER(H72)),F72*H72,"") -> 5000 | K72: =IF(AND(ISNUMBER(F72),ISNUMBER(I72)),F72*I72,"") | L72: Buying price may be USD 0.10 - verify
A73: 68 | B73: C | C73: Suckers, Cups & Gears | D73: Rubber Sucker 45 x 13 x 1 mm | F73: 500 | G73: Pcs | H73: 10 | J73: =IF(AND(ISNUMBER(F73),ISNUMBER(H73)),F73*H73,"") -> 5000 | K73: =IF(AND(ISNUMBER(F73),ISNUMBER(I73)),F73*I73,"") | L73: Buying price may be USD 0.10 - verify
A74: 69 | B74: C | C74: Suckers, Cups & Gears | D74: Cup Suckers White | F74: 500 | G74: Pcs | J74: =IF(AND(ISNUMBER(F74),ISNUMBER(H74)),F74*H74,"") | K74: =IF(AND(ISNUMBER(F74),ISNUMBER(I74)),F74*I74,"") | L74: No prices recorded
A75: 70 | B75: D | C75: Cam Followers & Bearings | D75: Cam Follower | E75: F-53125.02 | F75: 5 | G75: Pcs | H75: 55 | J75: =IF(AND(ISNUMBER(F75),ISNUMBER(H75)),F75*H75,"") -> 275 | K75: =IF(AND(ISNUMBER(F75),ISNUMBER(I75)),F75*I75,"") | L75: Buying price revised from USD 24 to USD 55
A76: 71 | B76: D | C76: Cam Followers & Bearings | D76: Cam Follower | E76: F-54293.1 | F76: 5 | G76: Pcs | J76: =IF(AND(ISNUMBER(F76),ISNUMBER(H76)),F76*H76,"") | K76: =IF(AND(ISNUMBER(F76),ISNUMBER(I76)),F76*I76,"") | L76: No prices recorded
A77: 72 | B77: D | C77: Cam Followers & Bearings | D77: Cam Follower | E77: F-53272 | F77: 5 | G77: Pcs | J77: =IF(AND(ISNUMBER(F77),ISNUMBER(H77)),F77*H77,"") | K77: =IF(AND(ISNUMBER(F77),ISNUMBER(I77)),F77*I77,"") | L77: No prices recorded
A78: 73 | B78: D | C78: Cam Followers & Bearings | D78: Cam Follower | E78: F-229817 | F78: 20 | G78: Pcs | H78: 30 | I78: 14750 | J78: =IF(AND(ISNUMBER(F78),ISNUMBER(H78)),F78*H78,"") -> 600 | K78: =IF(AND(ISNUMBER(F78),ISNUMBER(I78)),F78*I78,"") -> 295000
A79: 74 | B79: D | C79: Cam Followers & Bearings | D79: Cam Follower | E79: F-208089.02 | F79: 4 | G79: Pcs | H79: 26 | I79: 18500 | J79: =IF(AND(ISNUMBER(F79),ISNUMBER(H79)),F79*H79,"") -> 104 | K79: =IF(AND(ISNUMBER(F79),ISNUMBER(I79)),F79*I79,"") -> 74000
A80: 75 | B80: D | C80: Cam Followers & Bearings | D80: Cam Follower | E80: F-87592.03 | F80: 5 | G80: Pcs | H80: 38 | I80: 17750 | J80: =IF(AND(ISNUMBER(F80),ISNUMBER(H80)),F80*H80,"") -> 190 | K80: =IF(AND(ISNUMBER(F80),ISNUMBER(I80)),F80*I80,"") -> 88750
A81: 76 | B81: D | C81: Cam Followers & Bearings | D81: Cam Follower | E81: F-229818.01 | F81: 4 | G81: Pcs | H81: 113 | I81: 39500 | J81: =IF(AND(ISNUMBER(F81),ISNUMBER(H81)),F81*H81,"") -> 452 | K81: =IF(AND(ISNUMBER(F81),ISNUMBER(I81)),F81*I81,"") -> 158000
A82: 77 | B82: D | C82: Cam Followers & Bearings | D82: Cam Follower | E82: F-217813.04 | F82: 9 | G82: Pcs | H82: 24 | I82: 11250 | J82: =IF(AND(ISNUMBER(F82),ISNUMBER(H82)),F82*H82,"") -> 216 | K82: =IF(AND(ISNUMBER(F82),ISNUMBER(I82)),F82*I82,"") -> 101250 | L82: Cross-ref. 00.550.1471
A83: 78 | B83: D | C83: Cam Followers & Bearings | D83: Cam Follower | E83: F-222190 | F83: 14 | G83: Pcs | H83: 6 | I83: 6000 | J83: =IF(AND(ISNUMBER(F83),ISNUMBER(H83)),F83*H83,"") -> 84 | K83: =IF(AND(ISNUMBER(F83),ISNUMBER(I83)),F83*I83,"") -> 84000
A84: 79 | B84: D | C84: Cam Followers & Bearings | D84: Cam Follower | E84: F-513801 | F84: 2 | G84: Pcs | J84: =IF(AND(ISNUMBER(F84),ISNUMBER(H84)),F84*H84,"") | K84: =IF(AND(ISNUMBER(F84),ISNUMBER(I84)),F84*I84,"") | L84: No prices recorded
A85: 80 | B85: D | C85: Cam Followers & Bearings | D85: Cam Follower | E85: F-94474.01 | F85: 2 | G85: Pcs | H85: 20 | I85: 11500 | J85: =IF(AND(ISNUMBER(F85),ISNUMBER(H85)),F85*H85,"") -> 40 | K85: =IF(AND(ISNUMBER(F85),ISNUMBER(I85)),F85*I85,"") -> 23000
A86: 81 | B86: D | C86: Cam Followers & Bearings | D86: One Way Bearing | E86: HFL3030 | F86: 1 | G86: Pc | J86: =IF(AND(ISNUMBER(F86),ISNUMBER(H86)),F86*H86,"") | K86: =IF(AND(ISNUMBER(F86),ISNUMBER(I86)),F86*I86,"") | L86: No prices recorded
A87: 82 | B87: D | C87: Cam Followers & Bearings | D87: Cam Follower | E87: F-229025 | F87: 1 | G87: Pc | J87: =IF(AND(ISNUMBER(F87),ISNUMBER(H87)),F87*H87,"") | K87: =IF(AND(ISNUMBER(F87),ISNUMBER(I87)),F87*I87,"") | L87: Cross-ref. F2.011.121; no prices recorded
A88: 83 | B88: D | C88: Cam Followers & Bearings | D88: Cam Follower | E88: F-57439.02 | F88: 1 | G88: Pc | H88: 58.5 | J88: =IF(AND(ISNUMBER(F88),ISNUMBER(H88)),F88*H88,"") -> 58.5 | K88: =IF(AND(ISNUMBER(F88),ISNUMBER(I88)),F88*I88,"") | L88: Selling price not recorded
A89: 84 | B89: D | C89: Cam Followers & Bearings | D89: Bearing | E89: HK 1612-B | F89: 2 | G89: Pcs | J89: =IF(AND(ISNUMBER(F89),ISNUMBER(H89)),F89*H89,"") | K89: =IF(AND(ISNUMBER(F89),ISNUMBER(I89)),F89*I89,"") | L89: No prices recorded
A90: 85 | B90: D | C90: Cam Followers & Bearings | D90: Bearing | E90: HK 1012-AS1 | F90: 1 | G90: Pc | J90: =IF(AND(ISNUMBER(F90),ISNUMBER(H90)),F90*H90,"") | K90: =IF(AND(ISNUMBER(F90),ISNUMBER(I90)),F90*I90,"") | L90: No prices recorded
A91: 86 | B91: D | C91: Cam Followers & Bearings | D91: Bearing | E91: F-233282.01 | F91: 2 | G91: Pcs | H91: 32 | J91: =IF(AND(ISNUMBER(F91),ISNUMBER(H91)),F91*H91,"") -> 64 | K91: =IF(AND(ISNUMBER(F91),ISNUMBER(I91)),F91*I91,"") | L91: Selling price not recorded
A92: 87 | B92: D | C92: Cam Followers & Bearings | D92: Cam Follower | E92: F-237858.01 | G92: Pcs | J92: =IF(AND(ISNUMBER(F92),ISNUMBER(H92)),F92*H92,"") | K92: =IF(AND(ISNUMBER(F92),ISNUMBER(I92)),F92*I92,"") | L92: Quantity and prices not recorded
A93: 88 | B93: E | C93: Grippers, Pins & Blanket Hooks | D93: Gripper 76.5 x 13 x 3.5 mm | E93: S1127F-S | F93: 31 | G93: Pcs | H93: 3 | I93: 2350 | J93: =IF(AND(ISNUMBER(F93),ISNUMBER(H93)),F93*H93,"") -> 93 | K93: =IF(AND(ISNUMBER(F93),ISNUMBER(I93)),F93*I93,"") -> 72850 | L93: Buying price corrected from USD 30 to USD 3
A94: 89 | B94: E | C94: Grippers, Pins & Blanket Hooks | D94: Gripper 53 x 17 mm | E94: F3.023.010B | F94: 20 | G94: Pcs | H94: 3 | I94: 2350 | J94: =IF(AND(ISNUMBER(F94),ISNUMBER(H94)),F94*H94,"") -> 60 | K94: =IF(AND(ISNUMBER(F94),ISNUMBER(I94)),F94*I94,"") -> 47000
A95: 90 | B95: E | C95: Grippers, Pins & Blanket Hooks | D95: Impression Gripper | E95: 69.011.727 | F95: 29 | G95: Pcs | H95: 2 | I95: 1750 | J95: =IF(AND(ISNUMBER(F95),ISNUMBER(H95)),F95*H95,"") -> 58 | K95: =IF(AND(ISNUMBER(F95),ISNUMBER(I95)),F95*I95,"") -> 50750
A96: 91 | B96: E | C96: Grippers, Pins & Blanket Hooks | D96: Delivery Die Cutter Grippers | F96: 60 | G96: Pcs | H96: 2 | I96: 1850 | J96: =IF(AND(ISNUMBER(F96),ISNUMBER(H96)),F96*H96,"") -> 120 | K96: =IF(AND(ISNUMBER(F96),ISNUMBER(I96)),F96*I96,"") -> 111000
A97: 92 | B97: E | C97: Grippers, Pins & Blanket Hooks | D97: Swing Arm Gripper MO | F97: 10 | G97: Pcs | H97: 2 | I97: 1650 | J97: =IF(AND(ISNUMBER(F97),ISNUMBER(H97)),F97*H97,"") -> 20 | K97: =IF(AND(ISNUMBER(F97),ISNUMBER(I97)),F97*I97,"") -> 16500
A98: 93 | B98: E | C98: Grippers, Pins & Blanket Hooks | D98: Feed Gripper MO/SOR | F98: 20 | G98: Pcs | H98: 2 | I98: 1650 | J98: =IF(AND(ISNUMBER(F98),ISNUMBER(H98)),F98*H98,"") -> 40 | K98: =IF(AND(ISNUMBER(F98),ISNUMBER(I98)),F98*I98,"") -> 33000
A99: 94 | B99: E | C99: Grippers, Pins & Blanket Hooks | D99: Gripper MO/GTO/SM74 53 mm | F99: 64 | G99: Pcs | H99: 2 | I99: 1650 | J99: =IF(AND(ISNUMBER(F99),ISNUMBER(H99)),F99*H99,"") -> 128 | K99: =IF(AND(ISNUMBER(F99),ISNUMBER(I99)),F99*I99,"") -> 105600
A100: 95 | B100: E | C100: Grippers, Pins & Blanket Hooks | D100: Gripper Transfer | E100: C3.071.627 | F100: 28 | G100: Pcs | H100: 3.5 | I100: 2350 | J100: =IF(AND(ISNUMBER(F100),ISNUMBER(H100)),F100*H100,"") -> 98 | K100: =IF(AND(ISNUMBER(F100),ISNUMBER(I100)),F100*I100,"") -> 65800
A101: 96 | B101: E | C101: Grippers, Pins & Blanket Hooks | D101: Delivery Grippers Right | F101: 10 | G101: Pcs | H101: 5 | I101: 2300 | J101: =IF(AND(ISNUMBER(F101),ISNUMBER(H101)),F101*H101,"") -> 50 | K101: =IF(AND(ISNUMBER(F101),ISNUMBER(I101)),F101*I101,"") -> 23000
...

Sheet Summary by Column
A1: Summary by Register Column
A2: All figures calculated live from the 'Parts Inventory' tab.
A4: Column | B4: Category | C4: Line Items | D4: Total Qty | E4: Stock Value (USD) | F4: Potential Sales (KES)
A5: A | B5: Valves, Cylinders & Pistons | C5: =COUNTIFS('Parts Inventory'!$B$6:$B$139,$A5) -> 27 | D5: =SUMIFS('Parts Inventory'!$F$6:$F$139,'Parts Inventory'!$B$6:$B$139,$A5) -> 114 | E5: =SUMIFS('Parts Inventory'!$J$6:$J$139,'Parts Inventory'!$B$6:$B$139,$A5) -> 3338 | F5: =SUMIFS('Parts Inventory'!$K$6:$K$139,'Parts Inventory'!$B$6:$B$139,$A5) -> 1772120
A6: B | B6: Bellows, Diaphragms & Spindles | C6: =COUNTIFS('Parts Inventory'!$B$6:$B$139,$A6) -> 17 | D6: =SUMIFS('Parts Inventory'!$F$6:$F$139,'Parts Inventory'!$B$6:$B$139,$A6) -> 155 | E6: =SUMIFS('Parts Inventory'!$J$6:$J$139,'Parts Inventory'!$B$6:$B$139,$A6) -> 1540.1 | F6: =SUMIFS('Parts Inventory'!$K$6:$K$139,'Parts Inventory'!$B$6:$B$139,$A6) -> 1038245
A7: C | B7: Suckers, Cups & Gears | C7: =COUNTIFS('Parts Inventory'!$B$6:$B$139,$A7) -> 25 | D7: =SUMIFS('Parts Inventory'!$F$6:$F$139,'Parts Inventory'!$B$6:$B$139,$A7) -> 4834 | E7: =SUMIFS('Parts Inventory'!$J$6:$J$139,'Parts Inventory'!$B$6:$B$139,$A7) -> 13281.6 | F7: =SUMIFS('Parts Inventory'!$K$6:$K$139,'Parts Inventory'!$B$6:$B$139,$A7) -> 762010
A8: D | B8: Cam Followers & Bearings | C8: =COUNTIFS('Parts Inventory'!$B$6:$B$139,$A8) -> 18 | D8: =SUMIFS('Parts Inventory'!$F$6:$F$139,'Parts Inventory'!$B$6:$B$139,$A8) -> 83 | E8: =SUMIFS('Parts Inventory'!$J$6:$J$139,'Parts Inventory'!$B$6:$B$139,$A8) -> 2083.5 | F8: =SUMIFS('Parts Inventory'!$K$6:$K$139,'Parts Inventory'!$B$6:$B$139,$A8) -> 824000
A9: E | B9: Grippers, Pins & Blanket Hooks | C9: =COUNTIFS('Parts Inventory'!$B$6:$B$139,$A9) -> 28 | D9: =SUMIFS('Parts Inventory'!$F$6:$F$139,'Parts Inventory'!$B$6:$B$139,$A9) -> 920 | E9: =SUMIFS('Parts Inventory'!$J$6:$J$139,'Parts Inventory'!$B$6:$B$139,$A9) -> 1947 | F9: =SUMIFS('Parts Inventory'!$K$6:$K$139,'Parts Inventory'!$B$6:$B$139,$A9) -> 1632800
A10: F | B10: Springs, Screws & Ink Dividers | C10: =COUNTIFS('Parts Inventory'!$B$6:$B$139,$A10) -> 19 | D10: =SUMIFS('Parts Inventory'!$F$6:$F$139,'Parts Inventory'!$B$6:$B$139,$A10) -> 223 | E10: =SUMIFS('Parts Inventory'!$J$6:$J$139,'Parts Inventory'!$B$6:$B$139,$A10) -> 761.2 | F10: =SUMIFS('Parts Inventory'!$K$6:$K$139,'Parts Inventory'!$B$6:$B$139,$A10) -> 375650
A11: TOTAL | C11: =SUM(C5:C10) -> 134 | D11: =SUM(D5:D10) -> 6329 | E11: =SUM(E5:E10) -> 22951.4 | F11: =SUM(F5:F10) -> 6404825

Sheet Struck-Out Entries
A1: Entries Struck Through in the Register
A2: Kept for audit reference only. These lines are NOT counted as stock.
A4: Register Column | B4: Part Description | C4: Part No. | D4: Qty | E4: Unit | F4: Buying Price (USD) | G4: Selling Price (KES) | H4: Notes
A5: D | B5: Cam Follower | C5: F-229817.01 | E5: Pcs | F5: 30 | G5: 14750 | H5: Struck through in register
A6: E | B6: Delivery Gripper | D6: 100 | E6: Pcs | F6: 3.5 | G6: 2350 | H6: Struck through in register (duplicate of S1404F line)

Sheet Transcription Notes
A1: Transcription Notes & Assumptions
A3: Source | B3: Six photographs of the handwritten Printex Engineers parts register, labelled Column A through Column F.
A4: Currency | B4: Buying prices were written with a $ sign and are recorded as USD. Selling prices were written without a symbol in the thousands (e.g. 12,400.00) and are recorded as KES. Confirm before publishing a price list.
A5: Blank prices | B5: Several lines in the register have no buying price, no selling price, or neither. These cells are left blank rather than filled with zero, so totals reflect priced lines only.
A6: Struck-out lines | B6: Two lines were crossed out in the register. They are held on the 'Struck-Out Entries' tab and excluded from all totals.
A7: Price corrections | B7: Where a price was overwritten in the register, the later value is used and the change is recorded in the Notes column.
A8: Items to verify | B8: Handwriting was unclear on a small number of entries. Each is flagged in the Notes column of the inventory tab. The main ones are listed below.
A10: Tapered Pin 00.540.0081 (Col. E) | B10: Middle three digits are ambiguous - could read 00.500.0081.
A11: Diaphragm Clips CPI (Col. B) | B11: Trailing letters read as 'CPI'.
A12: Friction Wheels CPH (Col. B) | B12: Trailing letters read as 'CPh'.
A13: Worm Gear 42.006.029 (Col. C) | B13: Description read as 'Worm Gear' by comparison with the 'Gear Worm M2.006.001' line at the same buying price.
A14: Feeder Sucker Rod (Col. C) | B14: Buying price USD 10 exceeds the KES 100 selling price as written.
A15: Rubber Sucker 45 x 13 (Col. C) | B15: Buying price written as $10; all comparable suckers are priced at $0.10-$0.30, so this may be $0.10.
... A18: Cross-references | B18: Two margin notes in Column D have been carried into the Notes column: 00.550.1471 against F-217813.04, and F2.011.121 against F-229025.
